pyrtstools/__init__.py
pyrtstools/base.py
pyrtstools/features/__init__.py
pyrtstools/features/mfcc.py
pyrtstools/kws/__init__.py
pyrtstools/kws/_inferer.py
pyrtstools/kws/kws.py
pyrtstools/kws/kwsclient.py
pyrtstools/listenner/__init__.py
pyrtstools/listenner/listenner.py
pyrtstools/transform/__init__.py
pyrtstools/transform/bytesToNum.py
pyrtstools/transform/preEmphasis.py
pyrtstools/utils/__init__.py
pyrtstools/utils/wav.py
pyrtstools/vad/__init__.py
pyrtstools/vad/vad.py
pyrtstools-0.2.9.dist-info/DESCRIPTION.rst
pyrtstools-0.2.9.dist-info/METADATA
pyrtstools-0.2.9.dist-info/RECORD
pyrtstools-0.2.9.dist-info/WHEEL
pyrtstools-0.2.9.dist-info/metadata.json
pyrtstools-0.2.9.dist-info/top_level.txt
