Metadata-Version: 2.0
Name: pyrtstools
Version: 0.2.9
Summary: Tools for real time speech processing, keyword spotting
Home-page: https://github.com/linto-ai/pyrtstools.git
Author: Rudy Baraglia
Author-email: baraglia.rudy@gmail.com
License: AGPLv3+
Project-URL: github, https://github.com/linto-ai/pyrtstools.git
Project-URL: pypi, https://pypi.org/project/pyrtstools/
Keywords: kws hotword keyword vad utterance voice-command speech
Platform: UNKNOWN
Classifier: Programming Language :: Python :: 3
Classifier: Operating System :: OS Independent
Requires-Dist: numpy (>=1.16)
Requires-Dist: tensorflow (>=2.0.0)
Requires-Dist: pyaudio (>=0.2)
Requires-Dist: webrtcvad (>=2.0)
Requires-Dist: sonopy (>=0.1.2)
Requires-Dist: requests (>=2.22.0)
